metricflow_query/__init__.py
metricflow_query/cli.py
metricflow_query/materialize_metrics.py
metricflow_query/metricflow_query_materialize.sql
metricflow_query-1.0.0.dist-info/METADATA
metricflow_query-1.0.0.dist-info/WHEEL
metricflow_query-1.0.0.dist-info/entry_points.txt
metricflow_query-1.0.0.dist-info/RECORD
