Metadata-Version: 2.3
Name: metricflow-query
Version: 1.0.0
Summary: Build query for dbt metricflow
Author-email: Charlie <charile@linercorp.com>
Requires-Python: >=3.10
Requires-Dist: click>=7.1
Requires-Dist: dbt-core>=1.6.0
Requires-Dist: dbt-metricflow>=0.6.0
Requires-Dist: yaspin>=2
